rustc_dev_t_x64_win_msvc_nightly_p8/__init__.py
rustc_dev_t_x64_win_msvc_nightly_p8/data/darling_macro-4543ce35549bedf3.pdb
rustc_dev_t_x64_win_msvc_nightly_p8/data/derive_setters-a04de28c3cc0378a.dll.lib
rustc_dev_t_x64_win_msvc_nightly_p8/data/displaydoc-e6bf581cd9edd608.dll
rustc_dev_t_x64_win_msvc_nightly_p8/data/libarrayref-8a807d9977e4708c.rmeta
rustc_dev_t_x64_win_msvc_nightly_p8/data/libbstr-896586adbe7520f4.rmeta
rustc_dev_t_x64_win_msvc_nightly_p8/data/libfoldhash-2cd795749c425cef.rmeta
rustc_dev_t_x64_win_msvc_nightly_p8/data/libgetopts-a37401280b793ba6.rmeta
rustc_dev_t_x64_win_msvc_nightly_p8/data/libindexmap-b478236e028407c0.rmeta
rustc_dev_t_x64_win_msvc_nightly_p8/data/libjiff-77ce8a99efa0cc14.rmeta
rustc_dev_t_x64_win_msvc_nightly_p8/data/liblazy_static-46d9e573b6c482d6.rmeta
rustc_dev_t_x64_win_msvc_nightly_p8/data/liblibc-8d3ec61c0e2e1ca7.rmeta
rustc_dev_t_x64_win_msvc_nightly_p8/data/liblitemap-57a14703b248b33c.rmeta
rustc_dev_t_x64_win_msvc_nightly_p8/data/libmemchr-7c4e623e8a64c54e.rmeta
rustc_dev_t_x64_win_msvc_nightly_p8/data/libminiz_oxide-1e19bb73c934bd3d.rmeta
rustc_dev_t_x64_win_msvc_nightly_p8/data/libregex_automata-a9e32837f51a1549.rmeta
rustc_dev_t_x64_win_msvc_nightly_p8/data/librustc_arena-210265d1767f9918.rmeta
rustc_dev_t_x64_win_msvc_nightly_p8/data/librustc_data_structures-96b5b508297c3d9a.rmeta
rustc_dev_t_x64_win_msvc_nightly_p8/data/librustc_feature-c1ca719e3862f25d.rmeta
rustc_dev_t_x64_win_msvc_nightly_p8/data/librustc_hash-75ea718353207071.rmeta
rustc_dev_t_x64_win_msvc_nightly_p8/data/librustc_interface-b7455bb6647ec8ff.rmeta
rustc_dev_t_x64_win_msvc_nightly_p8/data/librustc_query_impl-194dd4562e5ca172.rmeta
rustc_dev_t_x64_win_msvc_nightly_p8/data/librustc_trait_selection-80d7bdf6f2f2b1ff.rmeta
rustc_dev_t_x64_win_msvc_nightly_p8/data/libserde_json-9943676202389149.rmeta
rustc_dev_t_x64_win_msvc_nightly_p8/data/libsharded_slab-a967baafae7f2df5.rmeta
rustc_dev_t_x64_win_msvc_nightly_p8-1.91.0.dist-info/METADATA
rustc_dev_t_x64_win_msvc_nightly_p8-1.91.0.dist-info/WHEEL
rustc_dev_t_x64_win_msvc_nightly_p8-1.91.0.dist-info/top_level.txt
rustc_dev_t_x64_win_msvc_nightly_p8-1.91.0.dist-info/RECORD
